Workbook
Name Slicer_customer_segment: #N/A
Name Slicer_market: #N/A

Sheet DASHBOARD
B2: SUPPLY CHAIN INTELLIGENCE DASHBOARD
B3: Delivery Performance · Customer Churn · Revenue Intelligence · 2015–2018
B5: =(GETPIVOTDATA("Sum of total_revenue",Calculations_!$A$3)) -> 74038161 | H5: =GETPIVOTDATA("Average of is_churned",Calculations_!$A$3) -> 0.43419524 | N5: =GETPIVOTDATA("Average of late_delivery_rate",Calculations_!$A$3) -> 0.61496136 | T5: =GETPIVOTDATA("Average of avg_satisfaction",Calculations_!$A$3) -> 2.0522172
B7: Total Revenue | H7: Churn Rate | N7: Late Deliveries | T7: Avg Satisfaction

Sheet REPORT
B3: SUPPLY CHAIN INTELLIGENCE
B5: Executive Report · DataCo Global Operations · 2015–2018
B8: EXECUTIVE SUMMARY - Analysis of 180,519 orders across 5 global markets reveals a critical revenue crisis. $50M has been lost to customer churn, 43% of customers have already churned, and 61% of all orders are delivered late. An estimated $12M in additional revenue remains at immediate risk. This report identifies root causes and provides three targeted interventions to halt further losses.
B14: $74M Total Revenue | G14: 43.4% Churn Rate | L14: 61% Late Deliveries | Q14: 2.05/5 Avg. Satisfaction
B20: 🔴 FINDING 1 — CRITICAL REVENUE LOSS
B21: $50,740,267 in revenue has been permanently lost to churned customers - 8,967 out of 20,652 customers (43.4%) have churned from the platform - Corporate segment shows highest churn rate at 44% — highest revenue at risk - Consumer segment accounts for largest absolute revenue loss at $6.2M CLV at risk RECOMMENDATION: Launch targeted Corporate retention program with dedicated account managers and contract incentives. Estimated revenue recovery: $3.7M annually.
B29: 🟡 FINDING 2 — SYSTEMIC DELIVERY FAILURE
B30: 61.5% of all 180,519 orders were delivered late — affecting every market globally - Late delivery is NOT a regional issue — all 5 markets show 54-56% late delivery rate - Pacific Asia (55.9%) and LATAM (55.8%) are worst performing markets - Fishing category ($6.9M revenue) — highest value category — most exposed to delay risk RECOMMENDATION: Renegotiate logistics SLAs with Pacific Asia & LATAM carriers. Implement real-time shipment tracking. Estimated late delivery reduction: 15-20%.
B38: 🔵 FINDING 3 — CUSTOMER EXPERIENCE CRISIS
B39: Average customer satisfaction score: 2.05 out of 5 — critically below acceptable threshold - Direct correlation identified: late deliveries → lower satisfaction → higher churn probability - Customers experiencing late deliveries are 2x more likely to churn within 90 days - $12M in projected CLV remains at risk from currently active high-risk customers RECOMMENDATION: Deploy proactive customer communication system for delayed orders. Introduce satisfaction recovery program (discount/priority shipping) for affected customers. Estimated churn reduction in at-risk segment: 12-15%.
B49: RECOMMENDED ACTION PLAN
B50: PRIORITY | E50: ACTION | H50: OWNER | K50: EST. IMPACT | N50: TIMELINE | Q50: STATUS
B51: 🔴 HIGH | E51: Corporate Retention Program | H51: Sales & CX Team | K51: $3.7M Recovery | N51: Q1 2024 | Q51: ⏳ Pending
B52: 🔴 HIGH | E52: Logistics SLA Renegotiation | H52: Operations | K52: -15% Late Delivery | N52: Q1 2024 | Q52: ⏳ Pending
B53: 🟡 MEDIUM | E53: Satisfaction Recovery Program | H53: CX Team | K53: -12% Churn Risk | N53: Q2 2024 | Q53: ⏳ Pending
B54: 🟡 MEDIUM | E54: Real-time Tracking System | H54: Tech Team | K54: 2x Satisfaction | N54: Q2 2024 | Q54: ⏳ Pending
B55: 🟢 LOW | E55: Fishing Category Protection | H55: Product Team | K55: $6.9M Protected | N55: Q3 2024 | Q55: ⏳ Pending
B58: Supply Chain Intelligence Report | DataCo Dataset — 180,519 Orders | Analysis Period: 2015–2018 | YUVRAJ SINGH KUSHWAH

Sheet CUSTOMER_DATA
A1: customer_id | B1: customer_segment | C1: customer_country | D1: total_orders | E1: total_revenue | F1: avg_order_value | G1: total_profit | H1: late_delivery_rate | I1: avg_delay_days | J1: total_complaints | K1: avg_satisfaction | L1: unresolved_complaints | M1: is_churned | N1: first_order_date | O1: last_order_date | P1: projected_clv | Q1: clv_tier
A2: 1 | B2: Consumer | C2: EE. UU. | D2: 1 | E2: 499.95 | F2: 499.95 | G2: 159.69 | H2: 1 | I2: 2 | J2: 1 | K2: 1 | L2: 1 | M2: 1 | N2: 2015-12-01 | O2: 2015-12-01 | P2: 749.92 | Q2: Silver
A3: 2 | B3: Consumer | C3: EE. UU. | D3: 4 | E3: 2919.67 | F3: 182.48 | G3: 356.22 | H3: 0.563 | I3: 1.1 | J3: 14 | K3: 3.36 | L3: 0 | M3: 0 | N3: 2015-08-10 | O3: 2017-09-17 | P3: 1094.88 | Q3: Silver
A4: 3 | B4: Consumer | C4: Puerto Rico | D4: 5 | E4: 3537.68 | F4: 196.54 | G4: 334.49 | H4: 0 | I4: -0.2 | J4: 5 | K4: 1 | L4: 5 | M4: 1 | N4: 2015-12-12 | O4: 2017-06-16 | P4: 1474.05 | Q4: Silver
A5: 4 | B5: Consumer | C5: EE. UU. | D5: 4 | E5: 4393.93 | F5: 118.75 | G5: -884.86 | H5: 0.919 | I5: 0.8 | J5: 37 | K5: 1.49 | L5: 22 | M5: 1 | N5: 2015-05-12 | O5: 2017-01-16 | P5: 712.5 | Q5: Silver
A6: 5 | B6: Home Office | C6: Puerto Rico | D6: 3 | E6: 3989.15 | F6: 181.33 | G6: 914.92 | H6: 0.909 | I6: 0.9 | J6: 21 | K6: 1.95 | L6: 6 | M6: 1 | N6: 2016-06-16 | O6: 2016-10-31 | P6: 815.98 | Q6: Silver
A7: 6 | B7: Consumer | C7: EE. UU. | D7: 4 | E7: 7918.77 | F7: 226.25 | G7: 2510.01 | H7: 0.857 | I7: 1.8 | J7: 30 | K7: 1.57 | L7: 10 | M7: 1 | N7: 2015-04-20 | O7: 2016-04-25 | P7: 1357.5 | Q7: Silver
A8: 7 | B8: Corporate | C8: Puerto Rico | D8: 7 | E8: 8349.08 | F8: 245.56 | G8: 1467.9 | H8: 0.618 | I8: 0.5 | J8: 21 | K8: 1.76 | L8: 12 | M8: 1 | N8: 2015-05-26 | O8: 2017-06-25 | P8: 2578.38 | Q8: Gold
A9: 8 | B9: Corporate | C9: EE. UU. | D9: 8 | E9: 3763.5 | F9: 198.08 | G9: 529.93 | H9: 0.211 | I9: -0.3 | J9: 11 | K9: 2.91 | L9: 0 | M9: 0 | N9: 2015-04-23 | O9: 2017-09-27 | P9: 2376.96 | Q9: Gold
A10: 9 | B10: Consumer | C10: Puerto Rico | D10: 5 | E10: 6834.32 | F10: 227.81 | G10: -1335.6 | H10: 1 | I10: 2.2 | J10: 29 | K10: 3 | L10: 3 | M10: 0 | N10: 2015-07-07 | O10: 2017-09-13 | P10: 1708.57 | Q10: Silver
A11: 10 | B11: Corporate | C11: EE. UU. | D11: 2 | E11: 2114.74 | F11: 176.23 | G11: -231.14 | H11: 0.667 | I11: 0.7 | J11: 8 | K11: 1 | L11: 0 | M11: 1 | N11: 2016-10-22 | O11: 2017-03-30 | P11: 528.69 | Q11: Silver
A12: 11 | B12: Consumer | C12: Puerto Rico | D12: 4 | E12: 3569.53 | F12: 209.97 | G12: 385.25 | H12: 0.588 | I12: 0.1 | J12: 10 | K12: 1.6 | L12: 6 | M12: 1 | N12: 2015-06-22 | O12: 2017-01-25 | P12: 1259.82 | Q12: Silver
A13: 12 | B13: Corporate | C13: EE. UU. | D13: 8 | E13: 9898.96 | F13: 219.98 | G13: 1785.48 | H13: 0.6 | I13: 0.4 | J13: 27 | K13: 1.19 | L13: 12 | M13: 1 | N13: 2015-01-14 | O13: 2017-05-21 | P13: 2639.76 | Q13: Gold
... A20653: 20757 | B20653: Corporate | C20653: EE. UU. | D20653: 1 | E20653: 39.75 | F20653: 39.75 | G20653: 9.79 | H20653: 1 | I20653: 1 | J20653: 0 | K20653: 1.83 | L20653: 0 | M20653: 0 | N20653: 2018-01-31 | O20653: 2018-01-31 | P20653: 59.62 | Q20653: Bronze

Sheet MONTHLY_DATA
A1: year_month | B1: total_orders | C1: total_revenue | D1: total_profit | E1: late_delivery_rate | F1: active_customers
A2: 2015-01 | B2: 1787 | C2: 1051590.1 | D2: 111660.74 | E2: 0.54114994 | F2: 1668
A3: 2015-02 | B3: 1585 | C3: 927009.88 | D3: 99140.66 | E3: 0.54853034 | F3: 1500
A4: 2015-03 | B4: 1781 | C4: 1051253.7 | D4: 113778.21 | E4: 0.54755688 | F4: 1654
A5: 2015-04 | B5: 1710 | C5: 1014463.3 | D5: 108083.68 | E5: 0.53843153 | F5: 1596
A6: 2015-05 | B6: 1776 | C6: 1050478.4 | D6: 112147.9 | E6: 0.55086802 | F6: 1654
A7: 2015-06 | B7: 1725 | C7: 1024006.2 | D7: 110147.16 | E7: 0.54109856 | F7: 1616
A8: 2015-07 | B8: 1763 | C8: 1038081.2 | D8: 115624.06 | E8: 0.55463295 | F8: 1628
A9: 2015-08 | B9: 1762 | C9: 1029494.7 | D9: 117979.77 | E9: 0.55679879 | F9: 1650
A10: 2015-09 | B10: 1706 | C10: 1018338.6 | D10: 113467.94 | E10: 0.56692607 | F10: 1608
A11: 2015-10 | B11: 1775 | C11: 1049154.2 | D11: 101757.87 | E11: 0.54809506 | F11: 1635
A12: 2015-11 | B12: 1729 | C12: 1029120.2 | D12: 104427.36 | E12: 0.54269341 | F12: 1604
A13: 2015-12 | B13: 1805 | C13: 1057840.9 | D13: 110641.55 | E13: 0.54682554 | F13: 1685
... A38: 2018-01 | B38: 2123 | C38: 331650.11 | D38: 33841.89 | E38: 0.56288271 | F38: 2123

Sheet MARKET_DATA
A1: market | B1: category_name | C1: total_orders | D1: total_revenue | E1: total_profit | F1: late_delivery_rate | G1: avg_delay | H1: unique_customers
A2: Africa | B2: Accessories | C2: 141 | D2: 11545.38 | E2: 1794.11 | F2: 0.61267606 | G2: 0.71830986 | H2: 140
A3: Africa | B3: Baseball & Softball | C3: 48 | D3: 8058.34 | E3: 701.77 | F3: 0.58 | G3: 0.7 | H3: 48
A4: Africa | B4: Boxing & MMA | C4: 31 | D4: 5222.15 | E4: -151.05 | F4: 0.58064516 | G4: 0.48387097 | H4: 31
A5: Africa | B5: Camping & Hiking | C5: 787 | D5: 265182.32 | E5: 25090 | F5: 0.52941176 | G5: 0.48529412 | H5: 758
A6: Africa | B6: Cardio Equipment | C6: 768 | D6: 257174.49 | E6: 33398.46 | F6: 0.54098361 | G6: 0.529274 | H6: 747
A7: Africa | B7: Cleats | C7: 1377 | D7: 298450.25 | E7: 31222.11 | F7: 0.54993983 | G7: 0.55054152 | H7: 1299
A8: Africa | B8: Electronics | C8: 242 | D8: 30256.42 | E8: 3129.23 | F8: 0.562249 | G8: 0.66666667 | H8: 237
A9: Africa | B9: Fishing | C9: 1033 | D9: 473976.3 | E9: 48234.46 | F9: 0.53670886 | G9: 0.52995781 | H9: 988
A10: Africa | B10: Fitness Accessories | C10: 24 | D10: 2659.24 | E10: 1.28 | F10: 0.44 | G10: 0.4 | H10: 24
A11: Africa | B11: Girls' Apparel | C11: 78 | D11: 10114.6 | E11: 1060.24 | F11: 0.6125 | G11: 0.8625 | H11: 77
A12: Africa | B12: Golf Apparel | C12: 30 | D12: 1859.07 | E12: 45.41 | F12: 0.53333333 | G12: 0.56666667 | H12: 30
A13: Africa | B13: Golf Balls | C13: 119 | D13: 6522.34 | E13: 382.99 | F13: 0.49166667 | G13: 0.6 | H13: 118
... A163: USCA | B163: Women's Apparel | C163: 2724 | D163: 478000 | E163: 60893.42 | F163: 0.55396579 | G163: 0.58009331 | H163: 2457

Sheet CALCULATIONS
A1: KPI | B1: Value | D1: Segment | E1: Churn Rate | F1: Revenue at Risk | H1: Market | I1: Late Delivery Rate | K1: Category | L1: Revenue
A2: Total Revenue | B2: =SUM(CUSTOMER_DATA!E2:E20653) -> 74038161 | D2: Consumer | E2: =COUNTIFS(CUSTOMER_DATA!B2:B20653,"Consumer",CUSTOMER_DATA!M2:M20653,1)/COUNTIF(CUSTOMER_DATA!B2:B20653,"Consumer") -> 0.43394109 | F2: {=SUMPRODUCT((CUSTOMER_DATA!B2:B20653="Consumer")*(CUSTOMER_DATA!M2:M20653=1)*CUSTOMER_DATA!P2:P20653)} -> 6232217.5 | H2: Africa | I2: 0.545 | K2: Fishing | L2: 6929654
A3: Total Profit | B3: =SUM(CUSTOMER_DATA!G2:G20653) -> 7868681.5 | D3: Corporate | E3: =COUNTIFS(CUSTOMER_DATA!B2:B20653,"Corporate",CUSTOMER_DATA!M2:M20653,1)/COUNTIF(CUSTOMER_DATA!B2:B20653,"Corporate") -> 0.43740984 | F3: {=SUMPRODUCT((CUSTOMER_DATA!B2:B20653="Corporate")*(CUSTOMER_DATA!M2:M20653=1)*CUSTOMER_DATA!P2:P20653)} -> 3692305.4 | H3: Europe | I3: 0.552 | K3: Cleats | L3: 4431943
A4: Revenue at Risk | B4: {=SUMPRODUCT((CUSTOMER_DATA!M2:M20653=1)*CUSTOMER_DATA!P2:P20653)} -> 12062618 | D4: Home Office | E4: =COUNTIFS(CUSTOMER_DATA!B2:B20653,"Home Office",CUSTOMER_DATA!M2:M20653,1)/COUNTIF(CUSTOMER_DATA!B2:B20653,"Home Office") -> 0.42953201 | F4: {=SUMPRODUCT((CUSTOMER_DATA!B2:B20653="Home Office")*(CUSTOMER_DATA!M2:M20653=1)*CUSTOMER_DATA!P2:P20653)} -> 2138095 | H4: LATAM | I4: 0.558 | K4: Camping & Hiking | L4: 4118425
A5: Revenue Lost | B5: {=SUMPRODUCT((CUSTOMER_DATA!M2:M20653=1)*CUSTOMER_DATA!E2:E20653)} -> 50740267 | H5: Pacific Asia | I5: 0.559 | K5: Cardio Equipment | L5: 3694843
A6: Total Customers | B6: =COUNTA(CUSTOMER_DATA!A2:A20653) -> 20652 | H6: USCA | I6: 0.556 | K6: Women's Apparel | L6: 3147800
A7: Churned Customers | B7: {=SUMPRODUCT((CUSTOMER_DATA!M2:M20653=1)*1)} -> 8967 | K7: Water Sports | L7: 3113845
A8: Churn Rate % | B8: =B7/B6 -> 0.43419524 | K8: Men's Footwear | L8: 2891758
A9: Avg. Late Delivery % | B9: =AVERAGE(CUSTOMER_DATA!H2:H20653) -> 0.61496136 | K9: Indoor/Outdoor Games | L9: 2888994
A10: Avg. Satisfaction | B10: =AVERAGE(CUSTOMER_DATA!K2:K20653) -> 2.0522172
A11: Profit Margin % | B11: =B3/B2 -> 0.10627873
A12: High Rish Customers | B12: {=SUMPRODUCT((CUSTOMER_DATA!M2:M20653=1)*1)} -> 8967

Sheet Calculations_
A3: Sum of total_revenue | B3: Average of is_churned | C3: Average of late_delivery_rate | D3: Average of avg_satisfaction | F3: Row Labels | G3: Sum of total_revenue | K3: Row Labels | L3: Average of late_delivery_rate | P3: Row Labels | Q3: Sum of total_revenue
A4: 74038161 | B4: 0.43419524 | C4: 0.61496136 | D4: 2.0522172 | F4: 2015-01 | G4: 1051590.1 | K4: Africa | L4: 0.54471634 | P4: Fishing | Q4: 6929653.5
F5: 2015-02 | G5: 927009.88 | K5: Europe | L5: 0.55179184 | P5: Cleats | Q5: 4431942.7
F6: 2015-03 | G6: 1051253.7 | K6: LATAM | L6: 0.55819842 | P6: Camping & Hiking | Q6: 4118425.4
F7: 2015-04 | G7: 1014463.3 | K7: Pacific Asia | L7: 0.55862555 | P7: Cardio Equipment | Q7: 3694843.2
F8: 2015-05 | G8: 1050478.4 | K8: USCA | L8: 0.55610888 | P8: Women's Apparel | Q8: 3147800
F9: 2015-06 | G9: 1024006.2 | K9: Grand Total | L9: 0.55438083 | P9: Water Sports | Q9: 3113844.6
F10: 2015-07 | G10: 1038081.2 | P10: Men's Footwear | Q10: 2891757.5
F11: 2015-08 | G11: 1029494.7 | P11: Indoor/Outdoor Games | Q11: 2888993.9
F12: 2015-09 | G12: 1018338.6 | P12: Grand Total | Q12: 31217261
F13: 2015-10 | G13: 1049154.2
F14: 2015-11 | G14: 1029120.2
F15: 2015-12 | G15: 1057840.9
F16: 2016-01 | G16: 1046308.2
F17: 2016-02 | G17: 968542.83
F18: 2016-03 | G18: 1025853.1
F19: 2016-04 | G19: 1001211.6
F20: 2016-05 | G20: 1029400.2
F21: 2016-06 | G21: 1003059.5
F22: 2016-07 | G22: 1045715.6
F23: 2016-08 | G23: 1048200.2
F24: 2016-09 | G24: 1002397
... F41: Grand Total | G41: 36784734
